pxr/.libs/PxrWork.dll
pxr/.libs/PxrWork.lib
pxr/Work/__init__.py
pxr/Work/_work.pyd
pxr_work-25.8.dist-info/METADATA
pxr_work-25.8.dist-info/WHEEL
pxr_work-25.8.dist-info/licenses/LICENSE.txt
pxr_work-25.8.dist-info/licenses/NOTICE.txt
pxr_work-25.8.dist-info/RECORD
