Metadata-Version: 2.4
Name: pxr-work
Version: 25.8
Summary: Multi-threaded dispatch library used in OpenUSD
Keywords: pixar,open-usd
License-File: LICENSE.txt
License-File: NOTICE.txt
Classifier: Programming Language :: Python :: 3
Classifier: Operating System :: POSIX :: Linux
Classifier: Operating System :: MacOS :: MacOS X
Classifier: Operating System :: Microsoft :: Windows :: Windows 10
Project-URL: Repository, https://github.com/untwine/pxr-work
Requires-Python: >=3.8
Requires-Dist: pxr-tf==25.8.*
Requires-Dist: pxr-trace==25.8.*
Requires-Dist: pxr-boost==25.8.*
Requires-Dist: pxr-tbb==2022.2.0.*
